README.md
setup.cfg
setup.py
distributions_dr123dr/Binomialdistribution.py
distributions_dr123dr/Gaussiandistribution.py
distributions_dr123dr/Generaldistribution.py
distributions_dr123dr/__init__.py
distributions_dr123dr.egg-info/PKG-INFO
distributions_dr123dr.egg-info/SOURCES.txt
distributions_dr123dr.egg-info/dependency_links.txt
distributions_dr123dr.egg-info/not-zip-safe
distributions_dr123dr.egg-info/top_level.txt